loafer/__init__.py
loafer/compat.py
loafer/dispatchers.py
loafer/exceptions.py
loafer/ext/__init__.py
loafer/ext/aws/__init__.py
loafer/ext/aws/bases.py
loafer/ext/aws/handlers.py
loafer/ext/aws/message_translators.py
loafer/ext/aws/providers.py
loafer/ext/aws/routes.py
loafer/ext/sentry.py
loafer/managers.py
loafer/message_translators.py
loafer/providers.py
loafer/routes.py
loafer/runners.py
loafer/utils.py
loafer_ng-3.0.0.dist-info/LICENSE
loafer_ng-3.0.0.dist-info/METADATA
loafer_ng-3.0.0.dist-info/WHEEL
loafer_ng-3.0.0.dist-info/RECORD
