Metadata-Version: 2.1
Name: loafer-ng
Version: 3.0.0
Summary: Asynchronous message dispatcher for concurrent tasks processing
Home-page: https://github.com/osantana/loafer
License: MIT
Author: George Y. Kussumoto
Author-email: contato@georgeyk.com.br
Maintainer: Osvaldo Santana Neto
Maintainer-email: loafer-ng@osantana.me
Requires-Python: >=3.10,<4.0
Classifier: License :: OSI Approved :: MIT License
Classifier: Programming Language :: Python :: 3
Classifier: Programming Language :: Python :: 3.10
Classifier: Programming Language :: Python :: 3.11
Requires-Dist: aiobotocore[boto3] (>=2.5.2,<3.0.0)
Requires-Dist: aiohttp (>=3.8.5,<4.0.0)
Requires-Dist: cached-property (>=1.5.2,<2.0.0)
Project-URL: Repository, https://github.com/osantana/loafer
